Metadata-Version: 1.1
Name: django-universe
Version: 2.8
Summary: A line of description for v0.8
Home-page: https://github.com/jerinzam/django-universe/
Author: jerin
Author-email: jerinzam@gmail.com
License: MIT
Download-URL: https://github.com/jerinzam/django-universe/tarball/0.8
Platform: UNKNOWN
